.bumpversion.cfg
.cookiecutterrc
.coveragerc
.editorconfig
.travis.yml
AUTHORS.rst
CHANGELOG.rst
CONTRIBUTING.rst
LICENSE
MANIFEST.in
README.rst
appveyor.yml
setup.cfg
setup.py
tox.ini
ci/appveyor-bootstrap.py
ci/appveyor-download.py
ci/appveyor-with-compiler.cmd
ci/bootstrap.py
ci/templates/.travis.yml
ci/templates/appveyor.yml
ci/templates/tox.ini
docs/authors.rst
docs/changelog.rst
docs/conf.py
docs/contributing.rst
docs/index.rst
docs/installation.rst
docs/readme.rst
docs/requirements.txt
docs/spelling_wordlist.txt
docs/usage.rst
docs/reference/componentry.rst
docs/reference/index.rst
src/componentry/__init__.py
src/componentry/_componentry.c
src/componentry.egg-info/PKG-INFO
src/componentry.egg-info/SOURCES.txt
src/componentry.egg-info/dependency_links.txt
src/componentry.egg-info/not-zip-safe
src/componentry.egg-info/top_level.txt
tests/test_componentry.py